{"@t":"2022-10-24T13:23:07.2576312Z","@mt":"Acquiring MainDom.","SourceContext":"Umbraco.Cms.Core.Runtime.MainDom","ProcessId":9952,"ProcessName":"MyWebsite","ThreadId":1,"ApplicationId":"c78dd8fa81105fc1a6655fcc7dea64a41e903f40","MachineName":"DESKTOP-DMDKT2M","Log4NetLevel":"INFO "}
{"@t":"2022-10-24T13:23:07.2785558Z","@mt":"Acquired MainDom.","SourceContext":"Umbraco.Cms.Core.Runtime.MainDom","ProcessId":9952,"ProcessName":"MyWebsite","ThreadId":1,"ApplicationId":"c78dd8fa81105fc1a6655fcc7dea64a41e903f40","MachineName":"DESKTOP-DMDKT2M","Log4NetLevel":"INFO "}
{"@t":"2022-10-24T13:23:08.2673677Z","@mt":"Now listening on: {address}","address":"https://localhost:44321","EventId":{"Id":14,"Name":"ListeningOnAddress"},"SourceContext":"Microsoft.Hosting.Lifetime","ProcessId":9952,"ProcessName":"MyWebsite","ThreadId":1,"ApplicationId":"c78dd8fa81105fc1a6655fcc7dea64a41e903f40","MachineName":"DESKTOP-DMDKT2M","Log4NetLevel":"INFO "}
{"@t":"2022-10-24T13:23:08.2676227Z","@mt":"Now listening on: {address}","address":"http://localhost:54980","EventId":{"Id":14,"Name":"ListeningOnAddress"},"SourceContext":"Microsoft.Hosting.Lifetime","ProcessId":9952,"ProcessName":"MyWebsite","ThreadId":1,"ApplicationId":"c78dd8fa81105fc1a6655fcc7dea64a41e903f40","MachineName":"DESKTOP-DMDKT2M","Log4NetLevel":"INFO "}
{"@t":"2022-10-24T13:23:08.2716766Z","@mt":"Application started. Press Ctrl+C to shut down.","SourceContext":"Microsoft.Hosting.Lifetime","ProcessId":9952,"ProcessName":"MyWebsite","ThreadId":1,"ApplicationId":"c78dd8fa81105fc1a6655fcc7dea64a41e903f40","MachineName":"DESKTOP-DMDKT2M","Log4NetLevel":"INFO "}
{"@t":"2022-10-24T13:23:08.2718161Z","@mt":"Hosting environment: {envName}","envName":"Development","SourceContext":"Microsoft.Hosting.Lifetime","ProcessId":9952,"ProcessName":"MyWebsite","ThreadId":1,"ApplicationId":"c78dd8fa81105fc1a6655fcc7dea64a41e903f40","MachineName":"DESKTOP-DMDKT2M","Log4NetLevel":"INFO "}
{"@t":"2022-10-24T13:23:08.2718905Z","@mt":"Content root path: {contentRoot}","contentRoot":"C:\\Users\\marwa\\Desktop\\umbraco\\MyWebsite","SourceContext":"Microsoft.Hosting.Lifetime","ProcessId":9952,"ProcessName":"MyWebsite","ThreadId":1,"ApplicationId":"c78dd8fa81105fc1a6655fcc7dea64a41e903f40","MachineName":"DESKTOP-DMDKT2M","Log4NetLevel":"INFO "}
